LICENSE
MANIFEST.in
README.md
package.json
setup.py
thinks_dash_storage_observer/__init__.py
thinks_dash_storage_observer/_imports_.py
thinks_dash_storage_observer.egg-info/PKG-INFO
thinks_dash_storage_observer.egg-info/SOURCES.txt
thinks_dash_storage_observer.egg-info/dependency_links.txt
thinks_dash_storage_observer.egg-info/top_level.txt